{
  "data": {
    "menu": {
      "__typename": "Menu",
      "allowReservation": true,
      "backgroundColor": null,
      "backgroundEffect": null,
      "backgroundImageUploadedPhoto": null,
      "backgroundImageUrl": null,
      "cateringLeadTimeMinutes": 0,
      "currency": "USD",
      "disclaimer": "*These foods are raw or can be served undercooked or contain (or may contain) raw or undercooked ingredients. \nConsuming raw or undercooked meats, poultry, seafood, shellfish, or eggs may increase your risk of foodborne illness.",
      "dishTags": [
        {
          "__typename": "RestaurantDishTag",
          "abbr": "GY",
          "color": "rgb(182, 167, 151)",
          "id": 77,
          "imageIconUrl": null,
          "name": "Gluten-Friendly"
        },
        {
          "__typename": "RestaurantDishTag",
          "abbr": "V ",
          "color": "rgba(15, 190, 50, 1)",
          "id": 4313,
          "imageIconUrl": null,
          "name": "Vegetarian"
        }
      ],
      "displayExtraGroups": false,
      "displayName": null,
      "displayPdfType": "pdf_none",
      "enabledFeaturedSection": null,
      "enabledSections": [
        {
          "__typename": "MenuSection",
          "backgroundColor": null,
          "description": "Available from 11:30 am \u2013 4 pm Monday \u2013 Friday",
          "enabledItemsCount": 0,
          "hasEnabledCustomHtml": false,
          "id": 423940,
          "isEnabled": true,
          "isFullWidth": false,
          "isHeaderEnabled": true,
          "isOrderingSection": false,
          "isSecret": false,
          "masterSectionId": 423939,
          "menuColumnCount": null,
          "menuLayout": null,
          "name": "Lunch Menu",
          "providerMenuSectionId": null,
          "slug": "lunch-menu"
        },
        {
          "__typename": "MenuSection",
          "backgroundColor": null,
          "description": null,
          "enabledItemsCount": 16,
          "hasEnabledCustomHtml": false,
          "id": 417973,
          "isEnabled": true,
          "isFullWidth": false,
          "isHeaderEnabled": true,
          "isOrderingSection": true,
          "isSecret": false,
          "masterSectionId": 417962,
          "menuColumnCount": null,
          "menuLayout": null,
          "name": "Appetizers",
          "providerMenuSectionId": null,
          "slug": "appetizers"
        },
        {
          "__typename": "MenuSection",
          "backgroundColor": null,
          "description": "Served on fire-grilled or gluten-free crust. ",
          "enabledItemsCount": 9,
          "hasEnabledCustomHtml": false,
          "id": 417974,
          "isEnabled": true,
          "isFullWidth": false,
          "isHeaderEnabled": true,
          "isOrderingSection": true,
          "isSecret": false,
          "masterSectionId": 417963,
          "menuColumnCount": null,
          "menuLayout": null,
          "name": "Flatbreads",
          "providerMenuSectionId": null,
          "slug": "flatbreads"
        },
        {
          "__typename": "MenuSection",
          "backgroundColor": null,
          "description": "Salad Additions:  Chicken 9 | Shrimp 14 | \"Jail Island\" Salmon* 15 | Grouper 17 | Skirt Steak 14 | Chilled Lump Crab 20 | Seared Yellowfin Tuna* 16",
          "enabledItemsCount": 11,
          "hasEnabledCustomHtml": false,
          "id": 417975,
          "isEnabled": true,
          "isFullWidth": false,
          "isHeaderEnabled": true,
          "isOrderingSection": true,
          "isSecret": false,
          "masterSectionId": 417964,
          "menuColumnCount": null,
          "menuLayout": null,
          "name": "Soup + Salad",
          "providerMenuSectionId": null,
          "slug": "soup-salad"
        },
        {
          "__typename": "MenuSection",
          "backgroundColor": null,
          "description": "Our variety of breads are hand-made from scratch in our own bakery and baked fresh every morning. Homemade gluten-free bread is available upon request. \nServed with fries, cole slaw or house chips. ",
          "enabledItemsCount": 13,
          "hasEnabledCustomHtml": false,
          "id": 417981,
          "isEnabled": true,
          "isFullWidth": false,
          "isHeaderEnabled": true,
          "isOrderingSection": true,
          "isSecret": false,
          "masterSectionId": 417970,
          "menuColumnCount": null,
          "menuLayout": null,
          "name": "Sandwiches",
          "providerMenuSectionId": null,
          "slug": "sandwiches"
        },
        {
          "__typename": "MenuSection",
          "backgroundColor": null,
          "description": "Our recipes are locally inspired with an emphasis on fresh, seasonal ingredients. Our chefs carefully hand cut our meats and prepare sauces from scratch every day.\nWe take great pride in serving the absolute freshest seafood. Our local Gulf Coast fish are selected daily, received whole and filleted by hand in our refrigerated\npreparation room.",
          "enabledItemsCount": 7,
          "hasEnabledCustomHtml": false,
          "id": 418033,
          "isEnabled": true,
          "isFullWidth": false,
          "isHeaderEnabled": true,
          "isOrderingSection": true,
          "isSecret": false,
          "masterSectionId": 418032,
          "menuColumnCount": null,
          "menuLayout": null,
          "name": "Entr\u00e9es",
          "providerMenuSectionId": null,
          "slug": "entrees"
        },
        {
          "__typename": "MenuSection",
          "backgroundColor": null,
          "description": null,
          "enabledItemsCount": 5,
          "hasEnabledCustomHtml": false,
          "id": 417982,
          "isEnabled": true,
          "isFullWidth": false,
          "isHeaderEnabled": true,
          "isOrderingSection": true,
          "isSecret": false,
          "masterSectionId": 417971,
          "menuColumnCount": null,
          "menuLayout": null,
          "name": "Sides",
          "providerMenuSectionId": null,
          "slug": "sides"
        },
        {
          "__typename": "MenuSection",
          "backgroundColor": null,
          "description": "Our desserts are made from scratch, using only the finest ingredients, by our own pastry chefs.",
          "enabledItemsCount": 8,
          "hasEnabledCustomHtml": false,
          "id": 417983,
          "isEnabled": true,
          "isFullWidth": false,
          "isHeaderEnabled": true,
          "isOrderingSection": true,
          "isSecret": false,
          "masterSectionId": 417972,
          "menuColumnCount": null,
          "menuLayout": null,
          "name": "Desserts",
          "providerMenuSectionId": null,
          "slug": "desserts"
        }
      ],
      "id": 71391,
      "isCateringMenu": false,
      "isEnabled": true,
      "isMenuHours": true,
      "isMenuHoursDelivery": false,
      "isOrderingDeliveryEnabled": false,
      "isOrderingDineInEnabled": false,
      "isOrderingEnabled": false,
      "itemBackgroundColor": null,
      "location": {
        "__typename": "RestaurantLocation",
        "allowReservations": true,
        "city": "Lakewood Ranch",
        "id": 11824,
        "isSquareMenuSyncEnabled": false,
        "isToastMenuSyncEnabled": true,
        "name": "GROVE",
        "openTableId": "1017463",
        "resyApiKey": null,
        "resyLinkUrl": null,
        "resyVenueId": null,
        "state": "FL",
        "toastRestaurant": {
          "__typename": "ToastRestaurant",
          "id": 154,
          "isSyncing": null
        },
        "yelpFriendlyId": null
      },
      "locationId": 11824,
      "masterMenuId": 71390,
      "menuColumnCount": null,
      "menuLayout": null,
      "menuOrderingUrl": null,
      "menuPageUrl": "/menu#menu=lunch",
      "menuSchemaMarkup": "{\"@context\":\"https://schema.org/\",\"@type\":\"Menu\",\"name\":\"Lunch\",\"url\":\"https://www.grovelwr.com/menu#menu=lunch\",\"hasMenuSection\":[{\"@type\":\"MenuSection\",\"description\":\"Available from 11:30 am \u2013 4 pm Monday \u2013 Friday\",\"name\":\"Lunch Menu\",\"hasMenuItem\":[]},{\"@type\":\"MenuSection\",\"name\":\"Appetizers\",\"hasMenuItem\":[{\"@type\":\"MenuItem\",\"description\":\"grouper, artichokes, Asiago, Parmesan, cream cheese, Old Bay, toasted pita\",\"image\":\"https://popmenucloud.com/cdn-cgi/image/width=1920,height=1920,format=auto,fit=scale-down/dxprkqlo/fbfcae8d-211e-41e5-b366-4ee1a35c7396.jpg\",\"name\":\"Grouper Artichoke Gratin\",\"offers\":{\"@type\":\"Offer\",\"price\":\"12.0\",\"priceCurrency\":\"USD\"},\"url\":\"https://www.grovelwr.com/items/grouper-artichoke-gratin-2?location=grove\\u0026menu=lunch\"},{\"@type\":\"MenuItem\",\"description\":\"bacon, melted Bleu cheese dressing, balsamic reduction, tomato,\\nscallion\",\"image\":\"https://popmenucloud.com/cdn-cgi/image/width=1920,height=1920,format=auto,fit=scale-down/dxprkqlo/2a8872fd-03e4-4367-887d-bd9ce7987fe6.jpg\",\"name\":\"Balsamic Chips\",\"offers\":{\"@type\":\"Offer\",\"price\":\"9.0\",\"priceCurrency\":\"USD\"},\"url\":\"https://www.grovelwr.com/items/balsamic-chips-3?location=grove\\u0026menu=lunch\"},{\"@type\":\"MenuItem\",\"description\":\"12 oz., bbq sauce, coleslaw\",\"name\":\"Smoked Baby Back Ribs\",\"offers\":{\"@type\":\"Offer\",\"price\":\"16.0\",\"priceCurrency\":\"USD\"},\"url\":\"https://www.grovelwr.com/items/smoked-baby-back-ribs?location=grove\\u0026menu=lunch\"},{\"@type\":\"MenuItem\",\"description\":\"12 oz., PEI mussels, white wine, garlic butter, spinach, Bleu cheese, bacon\",\"image\":\"https://popmenucloud.com/cdn-cgi/image/width=1920,height=1920,format=auto,fit=scale-down/dxprkqlo/54532e16-9d87-4b6b-966f-9793894e6c26.jpg\",\"name\":\"Mussels \\u0026 Bleu\",\"offers\":{\"@type\":\"Offer\",\"price\":\"15.0\",\"priceCurrency\":\"USD\"},\"url\":\"https://www.grovelwr.com/items/mussels-and-bleu-3?location=grove\\u0026menu=lunch\"},{\"@type\":\"MenuItem\",\"description\":\"roasted poblano ranch\",\"image\":\"https://popmenucloud.com/cdn-cgi/image/width=1920,height=1920,format=auto,fit=scale-down/dxprkqlo/253dea5c-a5f3-4974-a047-76f8e442522c.jpg\",\"name\":\"Fried Pickles\",\"offers\":{\"@type\":\"Offer\",\"price\":\"8.0\",\"priceCurrency\":\"USD\"},\"url\":\"https://www.grovelwr.com/items/fried-pickles-2?location=grove\\u0026menu=lunch\"},{\"@type\":\"MenuItem\",\"description\":\"Buffalo sauce, garlic and spices, carrots, Bleu cheese (7 pc)\",\"image\":\"https://popmenucloud.com/cdn-cgi/image/width=1920,height=1920,format=auto,fit=scale-down/dxprkqlo/e1f092c2-0abe-404c-9a4a-bbd689e7bebf.jpg\",\"name\":\"Annalida's Boneless Tenders\",\"offers\":{\"@type\":\"Offer\",\"price\":\"14.0\",\"priceCurrency\":\"USD\"},\"url\":\"https://www.grovelwr.com/items/annalidas-boneless-tenders-3?location=grove\\u0026menu=lunch\"},{\"@type\":\"MenuItem\",\"description\":\"smoked brisket, sweet bbq sauce, bacon jam, toasted brioche buns (3 pc)\",\"image\":\"https://popmenucloud.com/cdn-cgi/image/width=1920,height=1920,format=auto,fit=scale-down/dxprkqlo/15e2458e-07b0-44f9-8365-0db467257f6a.jpg\",\"name\":\"Brisket Sliders\",\"offers\":{\"@type\":\"Offer\",\"price\":\"13.0\",\"priceCurrency\":\"USD\"},\"url\":\"https://www.grovelwr.com/items/brisket-sliders-3?location=grove\\u0026menu=lunch\"},{\"@type\":\"MenuItem\",\"description\":\"Boursin, wine, garlic and puff pastry\\n\",\"image\":\"https://popmenucloud.com/cdn-cgi/image/width=1920,height=1920,format=auto,fit=scale-down/dxprkqlo/50b8f8d1-5731-42cd-b74c-1f02fec7b04b.jpg\",\"name\":\"Escargot\",\"offers\":{\"@type\":\"Offer\",\"price\":\"12.0\",\"priceCurrency\":\"USD\"},\"url\":\"https://www.grovelwr.com/items/escargot?location=grove\\u0026menu=lunch\"},{\"@type\":\"MenuItem\",\"description\":\"battered golden cod, chipotle cream, guajillo salsa, slaw (3 pc)\",\"name\":\"Fish Tacos\",\"offers\":{\"@type\":\"Offer\",\"price\":\"14.0\",\"priceCurrency\":\"USD\"},\"url\":\"https://www.grovelwr.com/items/fish-tacos?location=grove\\u0026menu=lunch\"},{\"@type\":\"MenuItem\",\"description\":\"8 oz., fried, Fresno chili peppers, soy mustard sauce, lemon\",\"image\":\"https://popmenucloud.com/cdn-cgi/image/width=1920,height=1920,format=auto,fit=scale-down/dxprkqlo/8c849d92-e7ad-492f-a176-897e1891d604.jpg\",\"name\":\"Point Judith Calamari\",\"offers\":{\"@type\":\"Offer\",\"price\":\"18.0\",\"priceCurrency\":\"USD\"},\"url\":\"https://www.grovelwr.com/items/point-judith-calamari?location=grove\\u0026menu=lunch\"},{\"@type\":\"MenuItem\",\"description\":\"6 oz., tempura battered cauliflower, spicy Thai sauce, green onion, peanuts \",\"image\":\"https://popmenucloud.com/cdn-cgi/image/width=1920,height=1920,format=auto,fit=scale-down/dxprkqlo/a7cc3719-d707-4f46-9562-cdeec44fb769.jpg\",\"name\":\"Thai Cauliflower\",\"offers\":{\"@type\":\"Offer\",\"price\":\"12.0\",\"priceCurrency\":\"USD\"},\"url\":\"https://www.grovelwr.com/items/thai-cauliflower-2?location=grove\\u0026menu=lunch\"},{\"@type\":\"MenuItem\",\"description\":\"seared Yellowfin tuna, wakame salad, avocado, soy glaze, Sriracha, spicy mustard aioli, sesame seeds, wonton chips\",\"image\":\"https://popmenucloud.com/cdn-cgi/image/width=1920,height=1920,format=auto,fit=scale-down/dxprkqlo/c5e15adc-2ab9-4e79-9196-448dca98ef36.jpg\",\"name\":\"Tuna Nachos*\",\"offers\":{\"@type\":\"Offer\",\"price\":\"18.0\",\"priceCurrency\":\"USD\"},\"url\":\"https://www.grovelwr.com/items/tuna-nachos-3?location=grove\\u0026menu=lunch\"},{\"@type\":\"MenuItem\",\"description\":\"bibb lettuce, ponzu chicken, ginger slaw, wasabi aioli, Sriracha and peanut sauce\",\"image\":\"https://popmenucloud.com/cdn-cgi/image/width=1920,height=1920,format=auto,fit=scale-down/dxprkqlo/824bbb5b-d1f5-4cce-bb24-cf2620b5927c.jpg\",\"name\":\"Asian Lettuce Wraps\",\"offers\":{\"@type\":\"Offer\",\"price\":\"16.0\",\"priceCurrency\":\"USD\"},\"url\":\"https://www.grovelwr.com/items/asian-lettuce-wraps?location=grove\\u0026menu=lunch\"},{\"@type\":\"MenuItem\",\"description\":\"Old Bay, cilantro cocktail sauce\",\"name\":\"Shrimp Cocktail\",\"offers\":{\"@type\":\"Offer\",\"price\":\"14.0\",\"priceCurrency\":\"USD\"},\"url\":\"https://www.grovelwr.com/items/shrimp-cocktail?location=grove\\u0026menu=lunch\"},{\"@type\":\"MenuItem\",\"description\":\"pickled watermelon, avocado, sushi rice,\\r\\nvegan yogurt, balsamic soy glaze\",\"name\":\"Watermelon Poke\",\"offers\":{\"@type\":\"Offer\",\"price\":\"9.0\",\"priceCurrency\":\"USD\"},\"url\":\"https://www.grovelwr.com/items/watermelon-poke?location=grove\\u0026menu=lunch\"},{\"@type\":\"MenuItem\",\"description\":\"sesame cumin crust, Sriracha, soy glaze, wasabi aioli, wakame salad\",\"image\":\"https://popmenucloud.com/cdn-cgi/image/width=1920,height=1920,format=auto,fit=scale-down/dxprkqlo/23d3cc5c-72e0-437f-a5d4-14ef89e7a266.jpg\",\"name\":\"Ahi Tuna\",\"offers\":{\"@type\":\"Offer\",\"price\":\"18.0\",\"priceCurrency\":\"USD\"},\"url\":\"https://www.grovelwr.com/items/ahi-tuna?location=grove\\u0026menu=lunch\"},{\"@type\":\"MenuItem\",\"description\":\"Slaw, house tartar sauce\",\"image\":\"https://popmenucloud.com/cdn-cgi/image/width=1920,height=1920,format=auto,fit=scale-down/dxprkqlo/bc724b13-8a11-41a6-871c-728083a3bc4a.jpg\",\"name\":\"Crab Cake\",\"offers\":{\"@type\":\"Offer\",\"price\":\"18.0\",\"priceCurrency\":\"USD\"},\"url\":\"https://www.grovelwr.com/items/crab-cake-2?location=grove\\u0026menu=lunch\"},{\"@type\":\"MenuItem\",\"description\":\"avocado, black beans, corn, red onion, pico de gallo, cotija cheese (3 pc)\",\"image\":\"https://popmenucloud.com/cdn-cgi/image/width=1920,height=1920,format=auto,fit=scale-down/dxprkqlo/3cc7cf58-ea9a-4d06-8229-96c88b1a75cc.jpg\",\"name\":\"Avocado Tacos\",\"offers\":{\"@type\":\"Offer\",\"price\":\"12.0\",\"priceCurrency\":\"USD\"},\"url\":\"https://www.grovelwr.com/items/avocado-tacos?location=grove\\u0026menu=lunch\"},{\"@type\":\"MenuItem\",\"description\":\"bacon, diced chicken, artichoke, Bleu cheese, Mozzarella, caramelized onion, garden wrap, poblano ranch, pico de gallo\",\"image\":\"https://popmenucloud.com/cdn-cgi/image/width=1920,height=1920,format=auto,fit=scale-down/dxprkqlo/0ce21a9b-6858-4afa-8d9f-ad00efc0164a.jpg\",\"name\":\"New Age Quesadilla\",\"offers\":{\"@type\":\"Offer\",\"price\":\"14.0\",\"priceCurrency\":\"USD\"},\"url\":\"https://www.grovelwr.com/items/new-age-quesadilla?location=grove\\u0026menu=lunch\"},{\"@type\":\"MenuItem\",\"description\":\"chicken and Asian vegetables tossed in sweet and spicy sauce\",\"name\":\"Sweet Thai Chicken\",\"offers\":{\"@type\":\"Offer\",\"price\":\"12.0\",\"priceCurrency\":\"USD\"},\"url\":\"https://www.grovelwr.com/items/sweet-thai-chicken?location=grove\\u0026menu=lunch\"},{\"@type\":\"MenuItem\",\"description\":\"Pimento cheese, candied bacon, scallions (5 pc)\",\"name\":\"Fried Green Tomatoes\",\"offers\":{\"@type\":\"Offer\",\"price\":\"12.0\",\"priceCurrency\":\"USD\"},\"url\":\"https://www.grovelwr.com/items/fried-green-tomatoes?location=grove\\u0026menu=lunch\"},{\"@type\":\"MenuItem\",\"description\":\"house-made chili sauce (5 pc)\",\"image\":\"https://popmenucloud.com/cdn-cgi/image/width=1920,height=1920,format=auto,fit=scale-down/dxprkqlo/69de9f6e-1218-4201-8d54-f1fb8c635de5.jpg\",\"name\":\"Veggie Spring Rolls\",\"offers\":{\"@type\":\"Offer\",\"price\":\"10.0\",\"priceCurrency\":\"USD\"},\"url\":\"https://www.grovelwr.com/items/veggie-spring-rolls?location=grove\\u0026menu=lunch\"}]},{\"@type\":\"MenuSection\",\"description\":\"Served on fire-grilled or gluten-free crust. \",\"name\":\"Flatbreads\",\"hasMenuItem\":[{\"@type\":\"MenuItem\",\"description\":\"sliced beef \\u0026 pork meatball, Ricotta cheese, marinara sauce, Mozzarella cheese, fresh basil, Parmesan\",\"name\":\"Meatball Flatbread\",\"offers\":{\"@type\":\"Offer\",\"price\":\"17.0\",\"priceCurrency\":\"USD\"},\"url\":\"https://www.grovelwr.com/items/meatball-flatbread?location=grove\\u0026menu=lunch\"},{\"@type\":\"MenuItem\",\"description\":\"Pimento cheese, cornmeal \\u0026 buttermilk crusted green tomatoes, pesto, candied bacon, scallions\",\"name\":\"Fried Green Tomato Flatbread\",\"offers\":{\"@type\":\"Offer\",\"price\":\"16.0\",\"priceCurrency\":\"USD\"},\"url\":\"https://www.grovelwr.com/items/fried-green-tomato-flatbread?location=grove\\u0026menu=lunch\"},{\"@type\":\"MenuItem\",\"description\":\"seared chicken, Goat cheese, Manchego, roasted red pepper, marinara, red onion, chimichurri\",\"image\":\"https://popmenucloud.com/cdn-cgi/image/width=1920,height=1920,format=auto,fit=scale-down/dxprkqlo/34d1c410-101c-4eca-a666-3af99aa6d42f.jpg\",\"name\":\"Chimi Chicken Flatbread\",\"offers\":{\"@type\":\"Offer\",\"price\":\"17.0\",\"priceCurrency\":\"USD\"},\"url\":\"https://www.grovelwr.com/items/chimi-chicken-flatbread-2?location=grove\\u0026menu=lunch\"},{\"@type\":\"MenuItem\",\"description\":\"Red onion, sweet bbq, Manchego, Mozzarella, cilantro\",\"image\":\"https://popmenucloud.com/cdn-cgi/image/width=1920,height=1920,format=auto,fit=scale-down/dxprkqlo/7c1bd4ee-1019-49a0-a0d5-bb5a73846f2c.jpg\",\"name\":\"BBQ Brisket Flatbread\",\"offers\":{\"@type\":\"Offer\",\"price\":\"18.0\",\"priceCurrency\":\"USD\"},\"url\":\"https://www.grovelwr.com/items/bbq-brisket-flatbread?location=grove\\u0026menu=lunch\"},{\"@type\":\"MenuItem\",\"description\":\"prosciutto, Brie, Granny Smith apple, Dijonnaise honey\",\"name\":\"Brie \\u0026 Apple Flatbread\",\"offers\":{\"@type\":\"Offer\",\"price\":\"14.0\",\"priceCurrency\":\"USD\"},\"url\":\"https://www.grovelwr.com/items/brie-and-apple-flatbread-3?location=grove\\u0026menu=lunch\"},{\"@type\":\"MenuItem\",\"description\":\"Mozzarella, sliced tomato, marinara, fresh basil \\n\",\"image\":\"https://popmenucloud.com/cdn-cgi/image/width=1920,height=1920,format=auto,fit=scale-down/dxprkqlo/8d5e2036-b357-4f59-b224-d3012e5e80db.jpg\",\"name\":\"Margherita Flatbread\",\"offers\":{\"@type\":\"Offer\",\"price\":\"13.0\",\"priceCurrency\":\"USD\"},\"url\":\"https://www.grovelwr.com/items/margherita-flatbread-2?location=grove\\u0026menu=lunch\"},{\"@type\":\"MenuItem\",\"description\":\"grilled chicken, bacon, artichoke, Bleu cheese, Mozzarella, Fontina, sweet onion\",\"image\":\"https://popmenucloud.com/cdn-cgi/image/width=1920,height=1920,format=auto,fit=scale-down/dxprkqlo/8d9649f3-503a-4ed5-9c27-24257d8e2080.jpg\",\"name\":\"New Age Flatbread\",\"offers\":{\"@type\":\"Offer\",\"price\":\"16.0\",\"priceCurrency\":\"USD\"},\"url\":\"https://www.grovelwr.com/items/new-age-flatbread-2?location=grove\\u0026menu=lunch\"},{\"@type\":\"MenuItem\",\"description\":\"pepperoni, marinara, Parmesan, Mozzarella\",\"image\":\"https://popmenucloud.com/cdn-cgi/image/width=1920,height=1920,format=auto,fit=scale-down/dxprkqlo/22953721-6122-47e1-8d38-ca29599964e2.jpg\",\"name\":\"Traditional Flatbread\",\"offers\":{\"@type\":\"Offer\",\"price\":\"15.0\",\"priceCurrency\":\"USD\"},\"url\":\"https://www.grovelwr.com/items/traditional-flatbread-2?location=grove\\u0026menu=lunch\"},{\"@type\":\"MenuItem\",\"description\":\"Tomato, garlic, basil, olive oil, arugula, Mozzarella, balsamic vinaigrette\",\"image\":\"https://popmenucloud.com/cdn-cgi/image/width=1920,height=1920,format=auto,fit=scale-down/dxprkqlo/f9464a0b-2b68-453d-ae33-e44bfb88f115.jpg\",\"name\":\"Bruschetta Flatbread\",\"offers\":{\"@type\":\"Offer\",\"price\":\"15.0\",\"priceCurrency\":\"USD\"},\"url\":\"https://www.grovelwr.com/items/bruschetta-flatbread-2?location=grove\\u0026menu=lunch\"}]},{\"@type\":\"MenuSection\",\"description\":\"Salad Additions:  Chicken 9 | Shrimp 14 | \\\"Jail Island\\\" Salmon* 15 | Grouper 17 | Skirt Steak 14 | Chilled Lump Crab 20 | Seared Yellowfin Tuna* 16\",\"name\":\"Soup + Salad\",\"hasMenuItem\":[{\"@type\":\"MenuItem\",\"name\":\"Soup of the Day\",\"offers\":{\"@type\":\"Offer\",\"price\":\"8.0\",\"priceCurrency\":\"USD\"},\"url\":\"https://www.grovelwr.com/items/soup-of-the-day?location=grove\\u0026menu=lunch\"},{\"@type\":\"MenuItem\",\"description\":\"Cream, potato, celery, onion, pancetta\",\"name\":\"New England Clam Chowder\",\"offers\":{\"@type\":\"Offer\",\"price\":\"8.0\",\"priceCurrency\":\"USD\"},\"url\":\"https://www.grovelwr.com/items/new-england-clam-chowder-2?location=grove\\u0026menu=lunch\"},{\"@type\":\"MenuItem\",\"description\":\"Caramelized sweet onions, fresh thyme, toasted croutons, melted Provolone\",\"name\":\"Baked Onion Soup\",\"offers\":{\"@type\":\"Offer\",\"price\":\"10.0\",\"priceCurrency\":\"USD\"},\"url\":\"https://www.grovelwr.com/items/baked-onion-soup?location=grove\\u0026menu=lunch\"},{\"@type\":\"MenuItem\",\"description\":\"beets, carrots, red onion, cucumbers, cherry tomato, Goat cheese, spring mix, balsamic vinaigrette\",\"image\":\"https://popmenucloud.com/cdn-cgi/image/width=1920,height=1920,format=auto,fit=scale-down/dxprkqlo/cd4a9dce-4c20-4b1e-b05a-357e6e0aabfe.jpg\",\"name\":\"House\",\"url\":\"https://www.grovelwr.com/items/house?location=grove\\u0026menu=lunch\"},{\"@type\":\"MenuItem\",\"description\":\"romaine, Parmesan, croutons, Caesar dressing\",\"name\":\"Caesar\",\"url\":\"https://www.grovelwr.com/items/caesar?location=grove\\u0026menu=lunch\"},{\"@type\":\"MenuItem\",\"description\":\"Goat cheese, carrots, mixed baby greens, balsamic vinaigrette\",\"image\":\"https://popmenucloud.com/cdn-cgi/image/width=1920,height=1920,format=auto,fit=scale-down/dxprkqlo/bf557c06-b300-47d4-a690-99266de97dff.jpg\",\"name\":\"Roasted Beet\",\"offers\":{\"@type\":\"Offer\",\"price\":\"12.0\",\"priceCurrency\":\"USD\"},\"url\":\"https://www.grovelwr.com/items/roasted-beet?location=grove\\u0026menu=lunch\"},{\"@type\":\"MenuItem\",\"description\":\"Red \\u0026 yellow tomato, Mozzarella, basil, balsamic glaze, olive oil, mixed baby greens\",\"name\":\"Mozzarella Caprese\",\"offers\":{\"@type\":\"Offer\",\"price\":\"15.0\",\"priceCurrency\":\"USD\"},\"url\":\"https://www.grovelwr.com/items/mozzarella-caprese?location=grove\\u0026menu=lunch\"},{\"@type\":\"MenuItem\",\"description\":\"strawberries, Goat cheese, mushroom, crispy onions, balsamic vinaigrette\",\"image\":\"https://popmenucloud.com/cdn-cgi/image/width=1920,height=1920,format=auto,fit=scale-down/dxprkqlo/03e63e19-e240-43ba-a65b-f25cf99a368d.jpg\",\"name\":\"Baby Spinach\",\"offers\":{\"@type\":\"Offer\",\"price\":\"12.0\",\"priceCurrency\":\"USD\"},\"url\":\"https://www.grovelwr.com/items/baby-spinach?location=grove\\u0026menu=lunch\"},{\"@type\":\"MenuItem\",\"description\":\"iceberg, bacon, Cheddar, sweet peas, red onion, cherry tomato, Bleu cheese\",\"image\":\"https://popmenucloud.com/cdn-cgi/image/width=1920,height=1920,format=auto,fit=scale-down/dxprkqlo/c640cb59-7a19-47e3-b581-4f05a9192fa5.jpg\",\"name\":\"Baby Wedge\",\"offers\":{\"@type\":\"Offer\",\"price\":\"12.0\",\"priceCurrency\":\"USD\"},\"url\":\"https://www.grovelwr.com/items/baby-wedge?location=grove\\u0026menu=lunch\"},{\"@type\":\"MenuItem\",\"description\":\"black bean corn salsa, avocado, Cheddar, tomatoes, hot Fresno peppers, corn tortilla strips, spring mix, romaine, poblano ranch\",\"image\":\"https://popmenucloud.com/cdn-cgi/image/width=1920,height=1920,format=auto,fit=scale-down/dxprkqlo/9fd2fb9a-1a34-4f5d-a249-e8ad00205ae6.jpg\",\"name\":\"Southwest Salad\",\"offers\":{\"@type\":\"Offer\",\"price\":\"12.0\",\"priceCurrency\":\"USD\"},\"url\":\"https://www.grovelwr.com/items/southwest-salad?location=grove\\u0026menu=lunch\"},{\"@type\":\"MenuItem\",\"description\":\"lobster, shrimp, crab, avocado, bacon, grape tomatoes, Bleu cheese, sweet peas, red onion, spring mix, green goddess dressing\",\"image\":\"https://popmenucloud.com/cdn-cgi/image/width=1920,height=1920,format=auto,fit=scale-down/dxprkqlo/eff4c641-b81a-405b-9676-33007c2a3a9f.jpg\",\"name\":\"Seafood Cobb\",\"offers\":{\"@type\":\"Offer\",\"price\":\"30.0\",\"priceCurrency\":\"USD\"},\"url\":\"https://www.grovelwr.com/items/seafood-cobb?location=grove\\u0026menu=lunch\"},{\"@type\":\"MenuItem\",\"description\":\"bacon, mushrooms, egg, red onion, Parmesan, croutons, romaine, Caesar dressing \",\"image\":\"https://popmenucloud.com/cdn-cgi/image/width=1920,height=1920,format=auto,fit=scale-down/dxprkqlo/346b9747-6dce-4066-b57c-9573c7c3be0a.jpg\",\"name\":\"Loaded Caesar\",\"offers\":{\"@type\":\"Offer\",\"price\":\"14.0\",\"priceCurrency\":\"USD\"},\"url\":\"https://www.grovelwr.com/items/loaded-caesar?location=grove\\u0026menu=lunch\"}]},{\"@type\":\"MenuSection\",\"description\":\"Our variety of breads are hand-made from scratch in our own bakery and baked fresh every morning. Homemade gluten-free bread is available upon request. \\nServed with fries, cole slaw or house chips. \",\"name\":\"Sandwiches\",\"hasMenuItem\":[{\"@type\":\"MenuItem\",\"description\":\"half pound certified Angus ground beef, house-made burger bun \",\"image\":\"https://popmenucloud.com/cdn-cgi/image/width=1920,height=1920,format=auto,fit=scale-down/dxprkqlo/2d1783bd-1e7f-4901-be69-cc1fc42c031b.jpg\",\"name\":\"Burger*\",\"offers\":{\"@type\":\"Offer\",\"price\":\"18.0\",\"priceCurrency\":\"USD\"},\"url\":\"https://www.grovelwr.com/items/burger?location=grove\\u0026menu=lunch\"},{\"@type\":\"MenuItem\",\"description\":\"half pound certified Angus ground beef, smoked brisket, white Cheddar, gravy, french fries, house-made burger bun\",\"image\":\"https://popmenucloud.com/cdn-cgi/image/width=1920,height=1920,format=auto,fit=scale-down/dxprkqlo/fddcc2a4-6a3e-47cb-b5a9-b92df4124aca.jpg\",\"name\":\"Poutine Burger*\",\"offers\":{\"@type\":\"Offer\",\"price\":\"21.0\",\"priceCurrency\":\"USD\"},\"url\":\"https://www.grovelwr.com/items/poutine-burger?location=grove\\u0026menu=lunch\"},{\"@type\":\"MenuItem\",\"description\":\"house-made black bean burger, panko, Provolone, basil mayo, house-made burger bun\",\"image\":\"https://popmenucloud.com/cdn-cgi/image/width=1920,height=1920,format=auto,fit=scale-down/dxprkqlo/b246c6e5-eefc-4b84-83d5-db3f15199884.jpg\",\"name\":\"Black Bean Burger\",\"offers\":{\"@type\":\"Offer\",\"price\":\"15.0\",\"priceCurrency\":\"USD\"},\"url\":\"https://www.grovelwr.com/items/black-bean-burger?location=grove\\u0026menu=lunch\"},{\"@type\":\"MenuItem\",\"description\":\"grilled, fried or blackened, house tartar sauce, house made bun\",\"name\":\"Grouper Sandwich\",\"offers\":{\"@type\":\"Offer\",\"price\":\"23.0\",\"priceCurrency\":\"USD\"},\"url\":\"https://www.grovelwr.com/items/grouper-sandwich-2?location=grove\\u0026menu=lunch\"},{\"@type\":\"MenuItem\",\"description\":\"fried grouper, white American, slaw, house tartar sauce, Texas toast\",\"name\":\"The Grouben\",\"offers\":{\"@type\":\"Offer\",\"price\":\"24.0\",\"priceCurrency\":\"USD\"},\"url\":\"https://www.grovelwr.com/items/the-grouben?location=grove\\u0026menu=lunch\"},{\"@type\":\"MenuItem\",\"description\":\"shaved roast pork, ham, Swiss, pickle, mustard\",\"image\":\"https://popmenucloud.com/cdn-cgi/image/width=1920,height=1920,format=auto,fit=scale-down/dxprkqlo/19c826d1-603c-422e-931d-04a54b2294c3.jpg\",\"name\":\"Pressed Cuban\",\"offers\":{\"@type\":\"Offer\",\"price\":\"15.0\",\"priceCurrency\":\"USD\"},\"url\":\"https://www.grovelwr.com/items/pressed-cuban?location=grove\\u0026menu=lunch\"},{\"@type\":\"MenuItem\",\"description\":\"blackened \\\"Jail Island\\\" salmon, Provolone, bacon, lettuce, tomato, avocado, pesto aioli, house-made Texas toast\",\"image\":\"https://popmenucloud.com/cdn-cgi/image/width=1920,height=1920,format=auto,fit=scale-down/dxprkqlo/5e12233d-953d-4431-b471-5f5be6c115ec.jpg\",\"name\":\"Salmon BLT Club\",\"offers\":{\"@type\":\"Offer\",\"price\":\"21.0\",\"priceCurrency\":\"USD\"},\"url\":\"https://www.grovelwr.com/items/salmon-blt-club?location=grove\\u0026menu=lunch\"},{\"@type\":\"MenuItem\",\"description\":\"shaved prime rib, Provolone, rosemary au jus, house-made Italian roll\",\"image\":\"https://popmenucloud.com/cdn-cgi/image/width=1920,height=1920,format=auto,fit=scale-down/dxprkqlo/e5fafd7f-c936-40ab-89ae-477cb0af3f98.jpg\",\"name\":\"French Dip\",\"offers\":{\"@type\":\"Offer\",\"price\":\"19.0\",\"priceCurrency\":\"USD\"},\"url\":\"https://www.grovelwr.com/items/french-dip?location=grove\\u0026menu=lunch\"},{\"@type\":\"MenuItem\",\"description\":\"chicken or tuna salad, lettuce, tomato, onion, pickle, house-made butter croissant\\n\",\"name\":\"Chilled Salad Croissant\",\"offers\":{\"@type\":\"Offer\",\"price\":\"15.0\",\"priceCurrency\":\"USD\"},\"url\":\"https://www.grovelwr.com/items/chilled-salad-croissant?location=grove\\u0026menu=lunch\"},{\"@type\":\"MenuItem\",\"description\":\"house sauce, lettuce, tomato, onion, pickle, house-made bun. Or Buffalo style with blue cheese.\",\"image\":\"https://popmenucloud.com/cdn-cgi/image/width=1920,height=1920,format=auto,fit=scale-down/dxprkqlo/23c51a03-6afb-4ebe-83e1-a3a6f9fb26bf.jpg\",\"name\":\"Southern Fried Chicken\",\"offers\":{\"@type\":\"Offer\",\"price\":\"16.0\",\"priceCurrency\":\"USD\"},\"url\":\"https://www.grovelwr.com/items/southern-fried-chicken?location=grove\\u0026menu=lunch\"},{\"@type\":\"MenuItem\",\"description\":\"corned beef, sauerkraut, Swiss cheese, 1,000 Island, house-made marble rye \\n\",\"image\":\"https://popmenucloud.com/cdn-cgi/image/width=1920,height=1920,format=auto,fit=scale-down/dxprkqlo/7c97a506-c838-4176-96cc-8b8cb5f6f821.jpg\",\"name\":\"Classic Reuben\",\"offers\":{\"@type\":\"Offer\",\"price\":\"15.0\",\"priceCurrency\":\"USD\"},\"url\":\"https://www.grovelwr.com/items/classic-reuben?location=grove\\u0026menu=lunch\"},{\"@type\":\"MenuItem\",\"description\":\"sliced smoked brisket, white American, caramelized onion, garlic aioli, pressed house-made Italian roll\",\"image\":\"https://popmenucloud.com/cdn-cgi/image/width=1920,height=1920,format=auto,fit=scale-down/dxprkqlo/23120e6c-ab1a-45c0-8eef-4891ceefd38e.jpg\",\"name\":\"Brisket Panini\",\"offers\":{\"@type\":\"Offer\",\"price\":\"19.0\",\"priceCurrency\":\"USD\"},\"url\":\"https://www.grovelwr.com/items/brisket-panini?location=grove\\u0026menu=lunch\"},{\"@type\":\"MenuItem\",\"description\":\"tuna salad, sliced tomato, Cheddar, house-made wheat bread\",\"name\":\"Tuna Melt\",\"offers\":{\"@type\":\"Offer\",\"price\":\"15.0\",\"priceCurrency\":\"USD\"},\"url\":\"https://www.grovelwr.com/items/tuna-melt?location=grove\\u0026menu=lunch\"},{\"@type\":\"MenuItem\",\"description\":\"Asian vegetables, chicken, sweet and spicy sauce, wrapped in a spinach tortilla\",\"name\":\"Thai Chicken Wrap\",\"offers\":{\"@type\":\"Offer\",\"price\":\"16.0\",\"priceCurrency\":\"USD\"},\"url\":\"https://www.grovelwr.com/items/thai-chicken-wrap?location=grove\\u0026menu=lunch\"},{\"@type\":\"MenuItem\",\"description\":\"grilled, poblano ranch, Cheddar cheese, avocado, house-made bun\",\"name\":\"Southwest Chicken Sandwich\",\"offers\":{\"@type\":\"Offer\",\"price\":\"16.0\",\"priceCurrency\":\"USD\"},\"url\":\"https://www.grovelwr.com/items/southwest-chicken-sandwich?location=grove\\u0026menu=lunch\"}]},{\"@type\":\"MenuSection\",\"description\":\"Our recipes are locally inspired with an emphasis on fresh, seasonal ingredients. Our chefs carefully hand cut our meats and prepare sauces from scratch every day.\\nWe take great pride in serving the absolute freshest seafood. Our local Gulf Coast fish are selected daily, received whole and filleted by hand in our refrigerated\\npreparation room.\",\"name\":\"Entr\u00e9es\",\"hasMenuItem\":[{\"@type\":\"MenuItem\",\"description\":\"sweet pea risotto, market veggies\",\"name\":\"Fresh Catch\",\"url\":\"https://www.grovelwr.com/items/fresh-catch?location=grove\\u0026menu=lunch\"},{\"@type\":\"MenuItem\",\"description\":\"tempura battered cod, house fries, house tartar sauce, slaw\",\"image\":\"https://popmenucloud.com/cdn-cgi/image/width=1920,height=1920,format=auto,fit=scale-down/dxprkqlo/ec14a570-ea1e-46a9-bc0d-70ba2bd7940e.jpg\",\"name\":\"Fish \\u0026 Chips\",\"offers\":{\"@type\":\"Offer\",\"price\":\"20.0\",\"priceCurrency\":\"USD\"},\"url\":\"https://www.grovelwr.com/items/fish-and-chips?location=grove\\u0026menu=lunch\"},{\"@type\":\"MenuItem\",\"description\":\"glazed salmon, sticky rice, asparagus\",\"image\":\"https://popmenucloud.com/cdn-cgi/image/width=1920,height=1920,format=auto,fit=scale-down/dxprkqlo/abade4df-b68c-4762-8847-d9a982b53cfb.jpg\",\"name\":\"Maple Ginger \u201cJail Island\u201d Salmon\",\"offers\":{\"@type\":\"Offer\",\"price\":\"32.0\",\"priceCurrency\":\"USD\"},\"url\":\"https://www.grovelwr.com/items/maple-ginger-jail-island-salmon?location=grove\\u0026menu=lunch\"},{\"@type\":\"MenuItem\",\"description\":\"slow cooked, sweet pea risotto, demi-glace, asparagus\\n\",\"image\":\"https://popmenucloud.com/cdn-cgi/image/width=1920,height=1920,format=auto,fit=scale-down/dxprkqlo/1680afcf-602c-4f38-b5d3-bdd3fd93cf33.jpg\",\"name\":\"Herb Chicken\",\"offers\":{\"@type\":\"Offer\",\"price\":\"26.0\",\"priceCurrency\":\"USD\"},\"url\":\"https://www.grovelwr.com/items/herb-chicken?location=grove\\u0026menu=lunch\"},{\"@type\":\"MenuItem\",\"description\":\"pancetta, snow peas, shiitake mushrooms, sun-dried tomato, Parmesan cream sauce\",\"image\":\"https://popmenucloud.com/cdn-cgi/image/width=1920,height=1920,format=auto,fit=scale-down/dxprkqlo/b832a197-4ad0-4423-876f-5538feba4e6c.jpg\",\"name\":\"Chicken Fusilli Pasta\",\"offers\":{\"@type\":\"Offer\",\"price\":\"26.0\",\"priceCurrency\":\"USD\"},\"url\":\"https://www.grovelwr.com/items/chicken-fusilli-pasta?location=grove\\u0026menu=lunch\"},{\"@type\":\"MenuItem\",\"description\":\"andouille sausage, chicken and trinity\\r\\nin a spicy tomato broth, white rice\",\"name\":\"Jambalaya\",\"offers\":{\"@type\":\"Offer\",\"price\":\"24.0\",\"priceCurrency\":\"USD\"},\"url\":\"https://www.grovelwr.com/items/jambalaya?location=grove\\u0026menu=lunch\"},{\"@type\":\"MenuItem\",\"description\":\"zucchini noodles, mushroom, marinara,\\r\\nspinach, olive oil, garlic\",\"name\":\"Zucchini Pasta\",\"offers\":{\"@type\":\"Offer\",\"price\":\"20.0\",\"priceCurrency\":\"USD\"},\"url\":\"https://www.grovelwr.com/items/zucchini-pasta?location=grove\\u0026menu=lunch\"}]},{\"@type\":\"MenuSection\",\"name\":\"Sides\",\"hasMenuItem\":[{\"@type\":\"MenuItem\",\"name\":\"House-Made French Fries\",\"offers\":{\"@type\":\"Offer\",\"price\":\"6.0\",\"priceCurrency\":\"USD\"},\"url\":\"https://www.grovelwr.com/items/house-made-french-fries?location=grove\\u0026menu=lunch\"},{\"@type\":\"MenuItem\",\"name\":\"House-Made Chips\",\"offers\":{\"@type\":\"Offer\",\"price\":\"5.0\",\"priceCurrency\":\"USD\"},\"url\":\"https://www.grovelwr.com/items/house-made-chips?location=grove\\u0026menu=lunch\"},{\"@type\":\"MenuItem\",\"name\":\"Cole Slaw\",\"offers\":{\"@type\":\"Offer\",\"price\":\"4.0\",\"priceCurrency\":\"USD\"},\"url\":\"https://www.grovelwr.com/items/cole-slaw?location=grove\\u0026menu=lunch\"},{\"@type\":\"MenuItem\",\"name\":\"Market Veggies\",\"offers\":{\"@type\":\"Offer\",\"price\":\"6.0\",\"priceCurrency\":\"USD\"},\"url\":\"https://www.grovelwr.com/items/market-veggies?location=grove\\u0026menu=lunch\"},{\"@type\":\"MenuItem\",\"name\":\"Sweet Pea Risotto\",\"offers\":{\"@type\":\"Offer\",\"price\":\"6.0\",\"priceCurrency\":\"USD\"},\"url\":\"https://www.grovelwr.com/items/sweet-pea-risotto?location=grove\\u0026menu=lunch\"},{\"@type\":\"MenuItem\",\"name\":\"Sticky Rice\",\"offers\":{\"@type\":\"Offer\",\"price\":\"5.0\",\"priceCurrency\":\"USD\"},\"url\":\"https://www.grovelwr.com/items/sticky-rice?location=grove\\u0026menu=lunch\"}]},{\"@type\":\"MenuSection\",\"description\":\"Our desserts are made from scratch, using only the finest ingredients, by our own pastry chefs.\",\"name\":\"Desserts\",\"hasMenuItem\":[{\"@type\":\"MenuItem\",\"description\":\"Creamy peanut butter mousse, Oreo crust, chocolate ganache\",\"image\":\"https://popmenucloud.com/cdn-cgi/image/width=1920,height=1920,format=auto,fit=scale-down/dxprkqlo/a13b09a8-2bce-4c8f-a422-b5806118e805.jpg\",\"name\":\"Peanut Butter Pie\",\"offers\":{\"@type\":\"Offer\",\"price\":\"9.0\",\"priceCurrency\":\"USD\"},\"url\":\"https://www.grovelwr.com/items/peanut-butter-pie?location=grove\\u0026menu=lunch\"},{\"@type\":\"MenuItem\",\"description\":\"triple chocolate mousse cake\",\"name\":\"Chocolate Cake\",\"offers\":{\"@type\":\"Offer\",\"price\":\"9.0\",\"priceCurrency\":\"USD\"},\"url\":\"https://www.grovelwr.com/items/chocolate-cake?location=grove\\u0026menu=lunch\"},{\"@type\":\"MenuItem\",\"description\":\"Granny Smith apples, cinnamon, crumb\\r\\ntopping with vanilla ice cream\",\"name\":\"Apple Cobbler\",\"offers\":{\"@type\":\"Offer\",\"price\":\"9.0\",\"priceCurrency\":\"USD\"},\"url\":\"https://www.grovelwr.com/items/apple-cobbler?location=grove\\u0026menu=lunch\"},{\"@type\":\"MenuItem\",\"description\":\"Key lime mousse, graham cracker crust\",\"name\":\"Key Lime Meringue Pie\",\"offers\":{\"@type\":\"Offer\",\"price\":\"9.0\",\"priceCurrency\":\"USD\"},\"url\":\"https://www.grovelwr.com/items/key-lime-meringue-pie?location=grove\\u0026menu=lunch\"},{\"@type\":\"MenuItem\",\"description\":\"cream cheese filling, graham cracker crust, blackberry compote\",\"name\":\"New York Style Cheesecake\",\"offers\":{\"@type\":\"Offer\",\"price\":\"9.0\",\"priceCurrency\":\"USD\"},\"url\":\"https://www.grovelwr.com/items/new-york-style-cheesecake?location=grove\\u0026menu=lunch\"},{\"@type\":\"MenuItem\",\"description\":\"Cream cheese icing, chopped pecans\",\"name\":\"Carrot Cake\",\"offers\":{\"@type\":\"Offer\",\"price\":\"9.0\",\"priceCurrency\":\"USD\"},\"url\":\"https://www.grovelwr.com/items/carrot-cake?location=grove\\u0026menu=lunch\"},{\"@type\":\"MenuItem\",\"description\":\"Pineapple, cinnamon brown sugar glaze, vanilla cake, cherry, served warm with ice cream\",\"image\":\"https://popmenucloud.com/cdn-cgi/image/width=1920,height=1920,format=auto,fit=scale-down/dxprkqlo/3ec0df81-deba-4e47-9082-8b9d0cf014d0.jpg\",\"name\":\"Pineapple Upside Down Cake\",\"offers\":{\"@type\":\"Offer\",\"price\":\"9.0\",\"priceCurrency\":\"USD\"},\"url\":\"https://www.grovelwr.com/items/pineapple-upside-down-cake?location=grove\\u0026menu=lunch\"},{\"@type\":\"MenuItem\",\"description\":\"Tahitian vanilla bean custard, crisp sugar crust\",\"name\":\"Cr\u00e8me Br\u00fbl\u00e9e\",\"offers\":{\"@type\":\"Offer\",\"price\":\"9.0\",\"priceCurrency\":\"USD\"},\"url\":\"https://www.grovelwr.com/items/creme-brulee-3?location=grove\\u0026menu=lunch\"}]}]}",
      "name": "Lunch",
      "pdfLinkUrl": null,
      "photoUploadedPhoto": null,
      "photoUrl": null,
      "popularMenuItems": [
        {
          "__typename": "MenuItem",
          "containsAlcohol": false,
          "currency": "USD",
          "customTaxRateId": null,
          "description": "grouper, artichokes, Asiago, Parmesan, cream cheese, Old Bay, toasted pita",
          "dish": {
            "__typename": "Dish",
            "allSelectedDishTags": [],
            "featured": false,
            "id": 754439,
            "isCreatedByMenuSync": false,
            "updateInProgress": false
          },
          "dishId": 754439,
          "extraGroups": [],
          "extras": [],
          "featured": false,
          "featuredPhoto": {
            "__typename": "Photo",
            "id": 221168,
            "photoUrl": "https://popmenucloud.com/cdn-cgi/image/width=1920,height=1920,format=auto,fit=scale-down/dxprkqlo/fbfcae8d-211e-41e5-b366-4ee1a35c7396.jpg",
            "thumbnailUrl": "https://popmenucloud.com/cdn-cgi/image/width=640,height=640,format=auto,fit=scale-down/dxprkqlo/fbfcae8d-211e-41e5-b366-4ee1a35c7396.jpg"
          },
          "htmlContent": null,
          "id": 2862839,
          "isDoordashDelivery": false,
          "isEnabled": true,
          "isOrderingEnabled": false,
          "isPoppable": true,
          "isTaxable": true,
          "likedItPopsCount": 0,
          "lovedItPopsCount": 0,
          "masterItemId": 2862733,
          "menu": {
            "__typename": "Menu",
            "cateringLeadTimeMinutes": 0,
            "id": 71391,
            "isCateringMenu": false,
            "locationId": 11824,
            "menuType": "menu_type_build"
          },
          "name": "Grouper Artichoke Gratin",
          "nextItem": {
            "__typename": "MenuItem",
            "id": 2862832,
            "name": "Balsamic Chips",
            "photosCount": 1
          },
          "outOfStock": false,
          "outOfStockUntil": null,
          "photos": [
            {
              "__typename": "Photo",
              "id": 221168,
              "photoHeight": 683,
              "photoUrl": "https://popmenucloud.com/cdn-cgi/image/width=1920,height=1920,format=auto,fit=scale-down/dxprkqlo/fbfcae8d-211e-41e5-b366-4ee1a35c7396.jpg",
              "photoWidth": 1024,
              "shareUrl": "https://popmenucloud.com/cdn-cgi/image/width=1200,height=630,format=auto,fit=cover/dxprkqlo/fbfcae8d-211e-41e5-b366-4ee1a35c7396.jpg",
              "thumbnailUrl": "https://popmenucloud.com/cdn-cgi/image/width=640,height=640,format=auto,fit=scale-down/dxprkqlo/fbfcae8d-211e-41e5-b366-4ee1a35c7396.jpg"
            }
          ],
          "photosCount": 1,
          "popsCount": 4,
          "previousItem": null,
          "price": 12.0,
          "priceCustomText": null,
          "priceType": "amount_price_type",
          "restaurant": {
            "__typename": "Restaurant",
            "allowAnonymousPops": true,
            "allowAnonymousReviews": false,
            "customDishTabContent": null,
            "customDishTabName": null,
            "followButtonCta": "Sign Up",
            "followHeadingCta": "Let's Stay In Touch!",
            "followSubheadingCta": "Be the first to receive updates on exclusive events, secret menus, special offers/discounts, loyalty rewards & more!",
            "id": 10125,
            "name": "GROVE"
          },
          "restaurantId": 10125,
          "reviewsCount": 0,
          "section": {
            "__typename": "MenuSection",
            "id": 417973,
            "menu": {
              "__typename": "Menu",
              "allowReservation": true,
              "cateringLeadTimeMinutes": 0,
              "id": 71391,
              "isCateringMenu": false,
              "location": {
                "__typename": "RestaurantLocation",
                "allowReservations": true,
                "city": "Lakewood Ranch",
                "customDishTabContent": "",
                "customDishTabName": "",
                "displayPhone": "(941) 893-4321",
                "email": null,
                "id": 11824,
                "isNcrSilverPayment": false,
                "isOrderingSpecialInstructionsEnabled": false,
                "name": "GROVE",
                "openTableId": "1017463",
                "phone": "9418934321",
                "postalCode": "34202",
                "resyApiKey": null,
                "resyLinkUrl": null,
                "resyVenueId": null,
                "slug": "grove",
                "state": "FL",
                "streetAddress": "10670 Boardwalk Loop",
                "yelpFriendlyId": null
              },
              "locationId": 11824,
              "menuOrderingUrl": null,
              "menuPageUrl": "/menu#menu=lunch",
              "name": "Lunch",
              "slug": "lunch",
              "url": "/menus/lunch?location=grove"
            },
            "name": "Appetizers"
          },
          "sharedExtraGroups": [],
          "shortLinkUrl": "https://popme.nu/ggad31",
          "showDisclaimer": false,
          "showFeaturedPhoto": true,
          "sizes": [],
          "slug": "grouper-artichoke-gratin-2",
          "subsection": {
            "__typename": "MenuSubsection",
            "id": 431055
          },
          "url": "/items/grouper-artichoke-gratin-2?location=grove&menu=lunch",
          "visitsCount": 0,
          "wannaTryPopsCount": 4
        },
        {
          "__typename": "MenuItem",
          "containsAlcohol": false,
          "currency": "USD",
          "customTaxRateId": null,
          "description": null,
          "dish": {
            "__typename": "Dish",
            "allSelectedDishTags": [],
            "featured": false,
            "id": 754449,
            "isCreatedByMenuSync": false,
            "updateInProgress": false
          },
          "dishId": 754449,
          "extraGroups": [],
          "extras": [],
          "featured": false,
          "featuredPhoto": null,
          "htmlContent": null,
          "id": 2862865,
          "isDoordashDelivery": false,
          "isEnabled": true,
          "isOrderingEnabled": false,
          "isPoppable": true,
          "isTaxable": true,
          "likedItPopsCount": 0,
          "lovedItPopsCount": 0,
          "masterItemId": 2862759,
          "menu": {
            "__typename": "Menu",
            "cateringLeadTimeMinutes": 0,
            "id": 71391,
            "isCateringMenu": false,
            "locationId": 11824,
            "menuType": "menu_type_build"
          },
          "name": "Soup of the Day",
          "nextItem": {
            "__typename": "MenuItem",
            "id": 2862866,
            "name": "New England Clam Chowder",
            "photosCount": 0
          },
          "outOfStock": false,
          "outOfStockUntil": null,
          "photos": [],
          "photosCount": 0,
          "popsCount": 0,
          "previousItem": {
            "__typename": "MenuItem",
            "id": 2862858,
            "name": "Bruschetta Flatbread",
            "photosCount": 1
          },
          "price": 8.0,
          "priceCustomText": null,
          "priceType": "amount_price_type",
          "restaurant": {
            "__typename": "Restaurant",
            "allowAnonymousPops": true,
            "allowAnonymousReviews": false,
            "customDishTabContent": null,
            "customDishTabName": null,
            "followButtonCta": "Sign Up",
            "followHeadingCta": "Let's Stay In Touch!",
            "followSubheadingCta": "Be the first to receive updates on exclusive events, secret menus, special offers/discounts, loyalty rewards & more!",
            "id": 10125,
            "name": "GROVE"
          },
          "restaurantId": 10125,
          "reviewsCount": 0,
          "section": {
            "__typename": "MenuSection",
            "id": 417975,
            "menu": {
              "__typename": "Menu",
              "allowReservation": true,
              "cateringLeadTimeMinutes": 0,
              "id": 71391,
              "isCateringMenu": false,
              "location": {
                "__typename": "RestaurantLocation",
                "allowReservations": true,
                "city": "Lakewood Ranch",
                "customDishTabContent": "",
                "customDishTabName": "",
                "displayPhone": "(941) 893-4321",
                "email": null,
                "id": 11824,
                "isNcrSilverPayment": false,
                "isOrderingSpecialInstructionsEnabled": false,
                "name": "GROVE",
                "openTableId": "1017463",
                "phone": "9418934321",
                "postalCode": "34202",
                "resyApiKey": null,
                "resyLinkUrl": null,
                "resyVenueId": null,
                "slug": "grove",
                "state": "FL",
                "streetAddress": "10670 Boardwalk Loop",
                "yelpFriendlyId": null
              },
              "locationId": 11824,
              "menuOrderingUrl": null,
              "menuPageUrl": "/menu#menu=lunch",
              "name": "Lunch",
              "slug": "lunch",
              "url": "/menus/lunch?location=grove"
            },
            "name": "Soup + Salad"
          },
          "sharedExtraGroups": [],
          "shortLinkUrl": "https://popme.nu/gsotd5",
          "showDisclaimer": false,
          "showFeaturedPhoto": true,
          "sizes": [],
          "slug": "soup-of-the-day",
          "subsection": {
            "__typename": "MenuSubsection",
            "id": 431057
          },
          "url": "/items/soup-of-the-day?location=grove&menu=lunch",
          "visitsCount": 0,
          "wannaTryPopsCount": 0
        },
        {
          "__typename": "MenuItem",
          "containsAlcohol": false,
          "currency": "USD",
          "customTaxRateId": null,
          "description": "half pound certified Angus ground beef, house-made burger bun ",
          "dish": {
            "__typename": "Dish",
            "allSelectedDishTags": [],
            "featured": false,
            "id": 754512,
            "isCreatedByMenuSync": false,
            "updateInProgress": false
          },
          "dishId": 754512,
          "extraGroups": [],
          "extras": [],
          "featured": false,
          "featuredPhoto": {
            "__typename": "Photo",
            "id": 221219,
            "photoUrl": "https://popmenucloud.com/cdn-cgi/image/width=1920,height=1920,format=auto,fit=scale-down/dxprkqlo/2d1783bd-1e7f-4901-be69-cc1fc42c031b.jpg",
            "thumbnailUrl": "https://popmenucloud.com/cdn-cgi/image/width=640,height=640,format=auto,fit=scale-down/dxprkqlo/2d1783bd-1e7f-4901-be69-cc1fc42c031b.jpg"
          },
          "htmlContent": null,
          "id": 2862915,
          "isDoordashDelivery": false,
          "isEnabled": true,
          "isOrderingEnabled": false,
          "isPoppable": true,
          "isTaxable": true,
          "likedItPopsCount": 0,
          "lovedItPopsCount": 4,
          "masterItemId": 2862809,
          "menu": {
            "__typename": "Menu",
            "cateringLeadTimeMinutes": 0,
            "id": 71391,
            "isCateringMenu": false,
            "locationId": 11824,
            "menuType": "menu_type_build"
          },
          "name": "Burger*",
          "nextItem": {
            "__typename": "MenuItem",
            "id": 2863569,
            "name": "Poutine Burger*",
            "photosCount": 1
          },
          "outOfStock": false,
          "outOfStockUntil": null,
          "photos": [
            {
              "__typename": "Photo",
              "id": 221219,
              "photoHeight": 1200,
              "photoUrl": "https://popmenucloud.com/cdn-cgi/image/width=1920,height=1920,format=auto,fit=scale-down/dxprkqlo/2d1783bd-1e7f-4901-be69-cc1fc42c031b.jpg",
              "photoWidth": 1800,
              "shareUrl": "https://popmenucloud.com/cdn-cgi/image/width=1200,height=630,format=auto,fit=cover/dxprkqlo/2d1783bd-1e7f-4901-be69-cc1fc42c031b.jpg",
              "thumbnailUrl": "https://popmenucloud.com/cdn-cgi/image/width=640,height=640,format=auto,fit=scale-down/dxprkqlo/2d1783bd-1e7f-4901-be69-cc1fc42c031b.jpg"
            }
          ],
          "photosCount": 1,
          "popsCount": 4,
          "previousItem": {
            "__typename": "MenuItem",
            "id": 2863561,
            "name": "Loaded Caesar",
            "photosCount": 1
          },
          "price": 18.0,
          "priceCustomText": null,
          "priceType": "amount_price_type",
          "restaurant": {
            "__typename": "Restaurant",
            "allowAnonymousPops": true,
            "allowAnonymousReviews": false,
            "customDishTabContent": null,
            "customDishTabName": null,
            "followButtonCta": "Sign Up",
            "followHeadingCta": "Let's Stay In Touch!",
            "followSubheadingCta": "Be the first to receive updates on exclusive events, secret menus, special offers/discounts, loyalty rewards & more!",
            "id": 10125,
            "name": "GROVE"
          },
          "restaurantId": 10125,
          "reviewsCount": 0,
          "section": {
            "__typename": "MenuSection",
            "id": 417981,
            "menu": {
              "__typename": "Menu",
              "allowReservation": true,
              "cateringLeadTimeMinutes": 0,
              "id": 71391,
              "isCateringMenu": false,
              "location": {
                "__typename": "RestaurantLocation",
                "allowReservations": true,
                "city": "Lakewood Ranch",
                "customDishTabContent": "",
                "customDishTabName": "",
                "displayPhone": "(941) 893-4321",
                "email": null,
                "id": 11824,
                "isNcrSilverPayment": false,
                "isOrderingSpecialInstructionsEnabled": false,
                "name": "GROVE",
                "openTableId": "1017463",
                "phone": "9418934321",
                "postalCode": "34202",
                "resyApiKey": null,
                "resyLinkUrl": null,
                "resyVenueId": null,
                "slug": "grove",
                "state": "FL",
                "streetAddress": "10670 Boardwalk Loop",
                "yelpFriendlyId": null
              },
              "locationId": 11824,
              "menuOrderingUrl": null,
              "menuPageUrl": "/menu#menu=lunch",
              "name": "Lunch",
              "slug": "lunch",
              "url": "/menus/lunch?location=grove"
            },
            "name": "Sandwiches"
          },
          "sharedExtraGroups": [
            {
              "__typename": "MenuItemSharedExtraGroup",
              "id": 745931,
              "isEnabled": true,
              "maxSelectionsCount": 1,
              "minSelectionsCount": 1,
              "position": 0,
              "sharedExtraGroup": {
                "__typename": "SharedExtraGroup",
                "extras": [
                  {
                    "__typename": "SharedExtraGroupExtra",
                    "id": 276565,
                    "isDefault": false,
                    "name": "Rare",
                    "outOfStock": false,
                    "outOfStockUntil": null,
                    "position": 0,
                    "price": null
                  },
                  {
                    "__typename": "SharedExtraGroupExtra",
                    "id": 276566,
                    "isDefault": false,
                    "name": "Medium Rare",
                    "outOfStock": false,
                    "outOfStockUntil": null,
                    "position": 1,
                    "price": null
                  },
                  {
                    "__typename": "SharedExtraGroupExtra",
                    "id": 276567,
                    "isDefault": false,
                    "name": "Medium",
                    "outOfStock": false,
                    "outOfStockUntil": null,
                    "position": 2,
                    "price": null
                  },
                  {
                    "__typename": "SharedExtraGroupExtra",
                    "id": 276568,
                    "isDefault": false,
                    "name": "Medium Well",
                    "outOfStock": false,
                    "outOfStockUntil": null,
                    "position": 3,
                    "price": null
                  },
                  {
                    "__typename": "SharedExtraGroupExtra",
                    "id": 276569,
                    "isDefault": false,
                    "name": "Well Done",
                    "outOfStock": false,
                    "outOfStockUntil": null,
                    "position": 4,
                    "price": null
                  }
                ],
                "id": 43330,
                "maxSelectionsCount": 1,
                "minSelectionsCount": 1,
                "multiSameSelection": false,
                "name": "Temperature"
              }
            },
            {
              "__typename": "MenuItemSharedExtraGroup",
              "id": 745114,
              "isEnabled": true,
              "maxSelectionsCount": 2,
              "minSelectionsCount": 0,
              "position": 1,
              "sharedExtraGroup": {
                "__typename": "SharedExtraGroup",
                "extras": [
                  {
                    "__typename": "SharedExtraGroupExtra",
                    "id": 276591,
                    "isDefault": false,
                    "name": "Gluten Free Bread",
                    "outOfStock": false,
                    "outOfStockUntil": null,
                    "position": null,
                    "price": null
                  },
                  {
                    "__typename": "SharedExtraGroupExtra",
                    "id": 276592,
                    "isDefault": false,
                    "name": "Vegan Bread",
                    "outOfStock": false,
                    "outOfStockUntil": null,
                    "position": null,
                    "price": null
                  }
                ],
                "id": 43337,
                "maxSelectionsCount": 2,
                "minSelectionsCount": 0,
                "multiSameSelection": false,
                "name": "Substitute Bread"
              }
            },
            {
              "__typename": "MenuItemSharedExtraGroup",
              "id": 745531,
              "isEnabled": true,
              "maxSelectionsCount": 1,
              "minSelectionsCount": 1,
              "position": 2,
              "sharedExtraGroup": {
                "__typename": "SharedExtraGroup",
                "extras": [
                  {
                    "__typename": "SharedExtraGroupExtra",
                    "id": 276475,
                    "isDefault": false,
                    "name": "Fries",
                    "outOfStock": false,
                    "outOfStockUntil": null,
                    "position": 0,
                    "price": null
                  },
                  {
                    "__typename": "SharedExtraGroupExtra",
                    "id": 276476,
                    "isDefault": false,
                    "name": "Cole Slaw",
                    "outOfStock": false,
                    "outOfStockUntil": null,
                    "position": 1,
                    "price": null
                  },
                  {
                    "__typename": "SharedExtraGroupExtra",
                    "id": 276477,
                    "isDefault": false,
                    "name": "House Chips",
                    "outOfStock": false,
                    "outOfStockUntil": null,
                    "position": 2,
                    "price": null
                  },
                  {
                    "__typename": "SharedExtraGroupExtra",
                    "id": 276478,
                    "isDefault": false,
                    "name": "Balsamic Chips",
                    "outOfStock": false,
                    "outOfStockUntil": null,
                    "position": 3,
                    "price": 2.0
                  },
                  {
                    "__typename": "SharedExtraGroupExtra",
                    "id": 276479,
                    "isDefault": false,
                    "name": "Fancy Fries",
                    "outOfStock": false,
                    "outOfStockUntil": null,
                    "position": 4,
                    "price": 2.0
                  },
                  {
                    "__typename": "SharedExtraGroupExtra",
                    "id": 276480,
                    "isDefault": false,
                    "name": "Fruit",
                    "outOfStock": false,
                    "outOfStockUntil": null,
                    "position": 5,
                    "price": 2.0
                  }
                ],
                "id": 43312,
                "maxSelectionsCount": 1,
                "minSelectionsCount": 1,
                "multiSameSelection": false,
                "name": "Side"
              }
            }
          ],
          "shortLinkUrl": "https://popme.nu/gb74f",
          "showDisclaimer": false,
          "showFeaturedPhoto": true,
          "sizes": [],
          "slug": "burger",
          "subsection": {
            "__typename": "MenuSubsection",
            "id": 431063
          },
          "url": "/items/burger?location=grove&menu=lunch",
          "visitsCount": 0,
          "wannaTryPopsCount": 0
        }
      ],
      "restaurant": {
        "__typename": "Restaurant",
        "id": 10125
      },
      "restaurantId": 10125,
      "selectedPrintLayout": null,
      "shortLinkUrl": "https://popme.nu/gl581",
      "slug": "lunch",
      "url": "/menus/lunch?location=grove"
    }
  }
}